{
    "domande": [
        {
            "Tipo": "Testo",
            "Contenuto": "Il film La dolce vita è uscito nel 1960?",
            "Risposta": true
        },
        {
            "Tipo": "Testo",
            "Contenuto": "Il film La dolce vita non è uscito nel 1950?",
            "Risposta": true
        },
        {
            "Tipo": "Testo",
            "Contenuto": "Marcello Mastroianni ha recitato nel film La dolce vita?",
            "Risposta": true
        },
        {
            "Tipo": "Foto",
            "Contenuto": "Fellini1",
            "Risposta": false
        },
        {
            "Tipo": "Video",
            "Contenuto": "Video1",
            "Risposta": true
        }
    ]
}
